checksums/__init__.py
checksums/calculate.py
checksums/cli.py
checksums-0.0.1.dist-info/METADATA
checksums-0.0.1.dist-info/WHEEL
checksums-0.0.1.dist-info/entry_points.txt
checksums-0.0.1.dist-info/top_level.txt
checksums-0.0.1.dist-info/RECORD
