Metadata-Version: 2.1
Name: checksums
Version: 0.0.1
Summary: A command line tool that show/verify checksums for a file.
Home-page: https://github.com/meowmeowmeowcat/checksums
Author: meowmeowcat
Author-email: 
License: UNKNOWN
Platform: UNKNOWN
Classifier: Programming Language :: Python :: 3
Classifier: License :: OSI Approved :: MIT License
Classifier: Operating System :: OS Independent
Requires-Python: >=3.6
Requires-Dist: click
